javeccli/__init__.py
javeccli/argsHandler.py
javec-0.1.4.dist-info/LICENSE
javec-0.1.4.dist-info/METADATA
javec-0.1.4.dist-info/WHEEL
javec-0.1.4.dist-info/entry_points.txt
javec-0.1.4.dist-info/top_level.txt
javec-0.1.4.dist-info/RECORD
