Metadata-Version: 2.1
Name: javec
Version: 0.1.4
Summary: Just another virtual environment creator
Home-page: https://github.com/BartlomiejF/JAVEC
Author: Bartlomiej Fliszkiewicz
Author-email: bartlomiej.fliszkiewicz.dev@gmail.com
License: MIT
Platform: UNKNOWN
